{
  "postList":[
    {
      "head": "https://sf3-ttcdn-tos.pstatp.com/img/user-avatar/fef4e13511ca2df5e92a8f83ca7cad57~120x256.image",
      "nickname": "无意穿堂风",
      "attention": true,
      "identityTag": "正能量萌新Yo主",
      "title": "该说不说, 农夫山泉这个搞的真不错",
      "images": [
        "https://pic4.zhimg.com/80/v2-3ca096e68ec4f22451e71b14b6facdf4_720w.jpg?source=1940ef5c",
        "https://pic1.zhimg.com/80/v2-a1c75773a3222f2241c15aab76d5bd54_720w.jpg?source=1940ef5c",
        "https://pic4.zhimg.com/80/v2-8f3a68350613d496cf0dd9eef30e3a73_720w.jpg?source=1940ef5c"
      ],
      "videos": null,
      "label": "最右每日讨论",
      "topComment": {
        "likeCount": 29120,
        "content": "空山不见人,\n但闻人语响。\n返景入深林, \n复照青苔上。",
        "images": null,
        "videos": null
      },
      "transpondCount": 780,
      "commentCount": 1520,
      "likeCount": 35251
    },
    {
      "head": "https://sf3-ttcdn-tos.pstatp.com/img/user-avatar/fef4e13511ca2df5e92a8f83ca7cad57~120x256.image",
      "nickname": "无意穿堂风",
      "attention": true,
      "identityTag": "正能量萌新Yo主",
      "title": "该说不说, 农夫山泉这个搞的真不错",
      "images": [
        "https://pic2.zhimg.com/80/v2-c654beb62b55c655d675c98abc74de8f_720w.jpg?source=1940ef5c",
        "https://pic4.zhimg.com/80/v2-9ec29054ecc05e46578b12aeb0558668_720w.jpg?source=1940ef5c",
        "https://pic2.zhimg.com/80/v2-3df76221fed1d401ba51e49ceb831137_720w.jpg?source=1940ef5c"
      ],
      "videos": null,
      "label": "最右每日讨论",
      "topComment": {
        "likeCount": 29120,
        "content": "空山不见人,\n但闻人语响。\n返景入深林, \n复照青苔上。",
        "images": null,
        "videos": null
      },
      "transpondCount": 780,
      "commentCount": 1520,
      "likeCount": 35251
    }
  ]
}